cert_sync.py
aws_cert_syncer-0.1.0.dist-info/LICENSE
aws_cert_syncer-0.1.0.dist-info/METADATA
aws_cert_syncer-0.1.0.dist-info/WHEEL
aws_cert_syncer-0.1.0.dist-info/entry_points.txt
aws_cert_syncer-0.1.0.dist-info/RECORD
