Metadata-Version: 2.3
Name: aws_cert_syncer
Version: 0.1.0
Summary: A robust tool to sync AWS ACM certificates to local files for web servers (nginx, apache, haproxy, etc.)
Keywords: aws,acm,ssl,certificates,nginx,apache,haproxy,docker,automation
Author: Koen Vossen
Author-email: info@koenvossen.nl
Requires-Python: >=3.9,<4.0
Classifier: Development Status :: 4 - Beta
Classifier: Intended Audience :: Developers
Classifier: Intended Audience :: System Administrators
Classifier: License :: OSI Approved :: MIT License
Classifier: Operating System :: OS Independent
Classifier: Programming Language :: Python :: 3
Classifier: Programming Language :: Python :: 3.9
Classifier: Programming Language :: Python :: 3.10
Classifier: Programming Language :: Python :: 3.11
Classifier: Programming Language :: Python :: 3.12
Classifier: Programming Language :: Python :: 3.13
Classifier: Topic :: Internet :: WWW/HTTP :: HTTP Servers
Classifier: Topic :: Security :: Cryptography
Classifier: Topic :: System :: Networking
Classifier: Topic :: System :: Systems Administration
Requires-Dist: boto3 (>=1.38.38,<2.0.0)
Requires-Dist: cryptography (>=41.0.0,<42.0.0)
Requires-Dist: pyyaml (>=6.0,<7.0)
Requires-Dist: schedule (>=1.2.0,<2.0.0)
Project-URL: Documentation, https://github.com/koenvo/aws_cert_syncer#readme
Project-URL: Homepage, https://github.com/koenvo/aws_cert_syncer
Project-URL: Repository, https://github.com/koenvo/aws_cert_syncer
